codereview_cli/__init__.py
codereview_cli/__main__.py
codereview_cli/__main__v1.py
codereview_cli-0.1.3.dist-info/METADATA
codereview_cli-0.1.3.dist-info/WHEEL
codereview_cli-0.1.3.dist-info/entry_points.txt
codereview_cli-0.1.3.dist-info/top_level.txt
codereview_cli-0.1.3.dist-info/RECORD
